odoo/addons/helpdesk_ticket_to_lead/CHANGELOG.md
odoo/addons/helpdesk_ticket_to_lead/README.rst
odoo/addons/helpdesk_ticket_to_lead/__init__.py
odoo/addons/helpdesk_ticket_to_lead/__manifest__.py
odoo/addons/helpdesk_ticket_to_lead/i18n/ca_ES.po
odoo/addons/helpdesk_ticket_to_lead/i18n/es.po
odoo/addons/helpdesk_ticket_to_lead/models/__init__.py
odoo/addons/helpdesk_ticket_to_lead/models/crm_lead.py
odoo/addons/helpdesk_ticket_to_lead/models/helpdesk_ticket.py
odoo/addons/helpdesk_ticket_to_lead/security/ir.model.access.csv
odoo/addons/helpdesk_ticket_to_lead/tests/__init__.py
odoo/addons/helpdesk_ticket_to_lead/tests/test_convert_to_lead.py
odoo/addons/helpdesk_ticket_to_lead/views/crm_lead_form_view.xml
odoo/addons/helpdesk_ticket_to_lead/views/helpdesk_ticket_to_lead.xml
odoo_addon_helpdesk_ticket_to_lead-16.0.1.0.0.dist-info/METADATA
odoo_addon_helpdesk_ticket_to_lead-16.0.1.0.0.dist-info/WHEEL
odoo_addon_helpdesk_ticket_to_lead-16.0.1.0.0.dist-info/top_level.txt
odoo_addon_helpdesk_ticket_to_lead-16.0.1.0.0.dist-info/RECORD
