Metadata-Version: 2.1
Name: odoo-addon-helpdesk_ticket_to_lead
Version: 16.0.1.0.0
Summary: Create CRM Leads from Helpdesk Tickets
Home-page: https://gitlab.com/somitcoop/erp-research/odoo-helpdesk
Author: Som It Cooperatiu SCCL, Som Connexió SCCL, Odoo Community Association (OCA)
Author-email: support@odoo-community.org
License: AGPL-3
Classifier: Programming Language :: Python
Classifier: Framework :: Odoo
Classifier: Framework :: Odoo :: 16.0
Classifier: License :: OSI Approved :: GNU Affero General Public License v3
Requires-Python: >=3.10
Requires-Dist: odoo-addon-helpdesk-mgmt <16.1dev,>=16.0dev
Requires-Dist: odoo <16.1dev,>=16.0a
